<?xml version="1.0"?>
<?mso-application progid="Excel.Sheet"?>
<Workbook xmlns="urn:schemas-microsoft-com:office:spreadsheet"
 xmlns:o="urn:schemas-microsoft-com:office:office"
 xmlns:x="urn:schemas-microsoft-com:office:excel"
 xmlns:dt="uuid:C2F41010-65B3-11d1-A29F-00AA00C14882"
 xmlns:ss="urn:schemas-microsoft-com:office:spreadsheet"
 xmlns:html="http://www.w3.org/TR/REC-html40">
 <DocumentProperties xmlns="urn:schemas-microsoft-com:office:office">
  <Author>Microsoft Office 用户</Author>
  <LastAuthor>fushuang</LastAuthor>
  <Created>2016-07-28T12:41:31Z</Created>
  <LastSaved>2019-12-17T02:51:51Z</LastSaved>
  <Version>16.00</Version>
 </DocumentProperties>
 <CustomDocumentProperties xmlns="urn:schemas-microsoft-com:office:office">
  <KSOProductBuildVer dt:dt="string">2052-10.1.0.7698</KSOProductBuildVer>
 </CustomDocumentProperties>
 <OfficeDocumentSettings xmlns="urn:schemas-microsoft-com:office:office">
  <AllowPNG/>
 </OfficeDocumentSettings>
 <ExcelWorkbook xmlns="urn:schemas-microsoft-com:office:excel">
  <WindowHeight>8916</WindowHeight>
  <WindowWidth>23040</WindowWidth>
  <WindowTopX>32767</WindowTopX>
  <WindowTopY>32767</WindowTopY>
  <ProtectStructure>False</ProtectStructure>
  <ProtectWindows>False</ProtectWindows>
 </ExcelWorkbook>
 <Styles>
  <Style ss:ID="Default" ss:Name="Normal">
   <Alignment ss:Vertical="Bottom"/>
   <Borders/>
   <Font ss:FontName="DengXian" ss:Size="12" ss:Color="#000000"/>
   <Interior/>
   <NumberFormat/>
   <Protection/>
  </Style>
  <Style ss:ID="s62" ss:Name="常规 2">
   <Alignment ss:Vertical="Bottom"/>
   <Borders/>
   <Font ss:FontName="宋体" x:CharSet="134" ss:Size="12" ss:Color="#000000"/>
   <Interior/>
   <NumberFormat/>
   <Protection/>
  </Style>
  <Style ss:ID="s63">
   <Interior ss:Color="#FCF305" ss:Pattern="Solid"/>
  </Style>
  <Style ss:ID="s64">
   <Interior ss:Color="#FFCC00" ss:Pattern="Solid"/>
  </Style>
 </Styles>
 <Worksheet ss:Name="工作表1">
  <Names>
   <NamedRange ss:Name="_FilterDatabase" ss:RefersTo="=工作表1!R1C1:R95C4"
    ss:Hidden="1"/>
  </Names>
  <Table ss:ExpandedColumnCount="4" ss:ExpandedRowCount="106" x:FullColumns="1"
   x:FullRows="1" ss:DefaultColumnWidth="64.8" ss:DefaultRowHeight="16.05">
   <Column ss:AutoFitWidth="0" ss:Width="136.19999999999999"/>
   <Column ss:Width="85.8"/>
   <Row ss:AutoFitHeight="0">
    <Cell ss:StyleID="s63"><Data ss:Type="String">key</Data><NamedCell
      ss:Name="_FilterDatabase"/></Cell>
    <Cell ss:StyleID="s63"><Data ss:Type="String">startVCode</Data><NamedCell
      ss:Name="_FilterDatabase"/></Cell>
    <Cell ss:StyleID="s63"><Data ss:Type="String">endVCode</Data><NamedCell
      ss:Name="_FilterDatabase"/></Cell>
    <Cell ss:StyleID="s63"><Data ss:Type="String">status</Data><NamedCell
      ss:Name="_FilterDatabase"/></Cell>
   </Row>
   <Row ss:AutoFitHeight="0">
    <Cell ss:StyleID="s64"><Data ss:Type="String">String</Data><NamedCell
      ss:Name="_FilterDatabase"/></Cell>
    <Cell ss:StyleID="s64"><Data ss:Type="String">Number</Data><NamedCell
      ss:Name="_FilterDatabase"/></Cell>
    <Cell ss:StyleID="s64"><Data ss:Type="String">Number</Data><NamedCell
      ss:Name="_FilterDatabase"/></Cell>
    <Cell ss:StyleID="s64"><Data ss:Type="String">Boolean</Data><NamedCell
      ss:Name="_FilterDatabase"/></Cell>
   </Row>
   <Row ss:AutoFitHeight="0">
    <Cell ss:StyleID="s62"><Data ss:Type="String">condition1</Data><NamedCell
      ss:Name="_FilterDatabase"/></Cell>
    <Cell><Data ss:Type="Number">74</Data><NamedCell ss:Name="_FilterDatabase"/></Cell>
    <Cell><Data ss:Type="Number">104</Data><NamedCell ss:Name="_FilterDatabase"/></Cell>
    <Cell><Data ss:Type="Boolean">1</Data><NamedCell ss:Name="_FilterDatabase"/></Cell>
   </Row>
   <Row ss:AutoFitHeight="0">
    <Cell ss:StyleID="s62"><Data ss:Type="String">condition2</Data><NamedCell
      ss:Name="_FilterDatabase"/></Cell>
    <Cell><Data ss:Type="Number">22</Data><NamedCell ss:Name="_FilterDatabase"/></Cell>
    <Cell><Data ss:Type="Number">94</Data><NamedCell ss:Name="_FilterDatabase"/></Cell>
    <Cell><Data ss:Type="Boolean">1</Data><NamedCell ss:Name="_FilterDatabase"/></Cell>
   </Row>
   <Row ss:AutoFitHeight="0">
    <Cell ss:StyleID="s62"><Data ss:Type="String">condition3</Data><NamedCell
      ss:Name="_FilterDatabase"/></Cell>
    <Cell><Data ss:Type="Number">77</Data><NamedCell ss:Name="_FilterDatabase"/></Cell>
    <Cell><Data ss:Type="Number">100</Data><NamedCell ss:Name="_FilterDatabase"/></Cell>
    <Cell><Data ss:Type="Boolean">1</Data><NamedCell ss:Name="_FilterDatabase"/></Cell>
   </Row>
   <Row ss:AutoFitHeight="0">
    <Cell ss:StyleID="s62"><Data ss:Type="String">condition4</Data><NamedCell
      ss:Name="_FilterDatabase"/></Cell>
    <Cell><Data ss:Type="Number">76</Data><NamedCell ss:Name="_FilterDatabase"/></Cell>
    <Cell><Data ss:Type="Number">94</Data><NamedCell ss:Name="_FilterDatabase"/></Cell>
    <Cell><Data ss:Type="Boolean">1</Data><NamedCell ss:Name="_FilterDatabase"/></Cell>
   </Row>
   <Row ss:AutoFitHeight="0">
    <Cell ss:StyleID="s62"><Data ss:Type="String">condition5</Data><NamedCell
      ss:Name="_FilterDatabase"/></Cell>
    <Cell><Data ss:Type="Number">78</Data><NamedCell ss:Name="_FilterDatabase"/></Cell>
    <Cell><Data ss:Type="Number">999999</Data><NamedCell ss:Name="_FilterDatabase"/></Cell>
    <Cell><Data ss:Type="Boolean">1</Data><NamedCell ss:Name="_FilterDatabase"/></Cell>
   </Row>
   <Row ss:AutoFitHeight="0">
    <Cell ss:StyleID="s62"><Data ss:Type="String">condition6</Data><NamedCell
      ss:Name="_FilterDatabase"/></Cell>
    <Cell><Data ss:Type="Number">78</Data><NamedCell ss:Name="_FilterDatabase"/></Cell>
    <Cell><Data ss:Type="Number">91</Data><NamedCell ss:Name="_FilterDatabase"/></Cell>
    <Cell><Data ss:Type="Boolean">1</Data><NamedCell ss:Name="_FilterDatabase"/></Cell>
   </Row>
   <Row ss:AutoFitHeight="0">
    <Cell ss:StyleID="s62"><Data ss:Type="String">condition7</Data><NamedCell
      ss:Name="_FilterDatabase"/></Cell>
    <Cell><Data ss:Type="Number">87</Data><NamedCell ss:Name="_FilterDatabase"/></Cell>
    <Cell><Data ss:Type="Number">91</Data><NamedCell ss:Name="_FilterDatabase"/></Cell>
    <Cell><Data ss:Type="Boolean">1</Data><NamedCell ss:Name="_FilterDatabase"/></Cell>
   </Row>
   <Row ss:AutoFitHeight="0">
    <Cell ss:StyleID="s62"><Data ss:Type="String">condition8</Data><NamedCell
      ss:Name="_FilterDatabase"/></Cell>
    <Cell><Data ss:Type="Number">84</Data><NamedCell ss:Name="_FilterDatabase"/></Cell>
    <Cell><Data ss:Type="Number">92</Data><NamedCell ss:Name="_FilterDatabase"/></Cell>
    <Cell><Data ss:Type="Boolean">1</Data><NamedCell ss:Name="_FilterDatabase"/></Cell>
   </Row>
   <Row ss:AutoFitHeight="0">
    <Cell ss:StyleID="s62"><Data ss:Type="String">condition9</Data><NamedCell
      ss:Name="_FilterDatabase"/></Cell>
    <Cell><Data ss:Type="Number">92</Data><NamedCell ss:Name="_FilterDatabase"/></Cell>
    <Cell><Data ss:Type="Number">103</Data><NamedCell ss:Name="_FilterDatabase"/></Cell>
    <Cell><Data ss:Type="Boolean">1</Data><NamedCell ss:Name="_FilterDatabase"/></Cell>
   </Row>
   <Row ss:AutoFitHeight="0">
    <Cell ss:StyleID="s62"><Data ss:Type="String">condition10</Data><NamedCell
      ss:Name="_FilterDatabase"/></Cell>
    <Cell><Data ss:Type="Number">91</Data><NamedCell ss:Name="_FilterDatabase"/></Cell>
    <Cell><Data ss:Type="Number">106</Data><NamedCell ss:Name="_FilterDatabase"/></Cell>
    <Cell><Data ss:Type="Boolean">1</Data><NamedCell ss:Name="_FilterDatabase"/></Cell>
   </Row>
   <Row ss:AutoFitHeight="0">
    <Cell ss:StyleID="s62"><Data ss:Type="String">condition11</Data><NamedCell
      ss:Name="_FilterDatabase"/></Cell>
    <Cell><Data ss:Type="Number">92</Data><NamedCell ss:Name="_FilterDatabase"/></Cell>
    <Cell><Data ss:Type="Number">100</Data><NamedCell ss:Name="_FilterDatabase"/></Cell>
    <Cell><Data ss:Type="Boolean">1</Data><NamedCell ss:Name="_FilterDatabase"/></Cell>
   </Row>
   <Row ss:AutoFitHeight="0">
    <Cell ss:StyleID="s62"><Data ss:Type="String">condition12</Data><NamedCell
      ss:Name="_FilterDatabase"/></Cell>
    <Cell><Data ss:Type="Number">91</Data><NamedCell ss:Name="_FilterDatabase"/></Cell>
    <Cell><Data ss:Type="Number">98</Data><NamedCell ss:Name="_FilterDatabase"/></Cell>
    <Cell><Data ss:Type="Boolean">1</Data><NamedCell ss:Name="_FilterDatabase"/></Cell>
   </Row>
   <Row ss:AutoFitHeight="0">
    <Cell ss:StyleID="s62"><Data ss:Type="String">condition13</Data><NamedCell
      ss:Name="_FilterDatabase"/></Cell>
    <Cell><Data ss:Type="Number">91</Data><NamedCell ss:Name="_FilterDatabase"/></Cell>
    <Cell><Data ss:Type="Number">99</Data><NamedCell ss:Name="_FilterDatabase"/></Cell>
    <Cell><Data ss:Type="Boolean">1</Data><NamedCell ss:Name="_FilterDatabase"/></Cell>
   </Row>
   <Row ss:AutoFitHeight="0">
    <Cell ss:StyleID="s62"><Data ss:Type="String">condition14</Data><NamedCell
      ss:Name="_FilterDatabase"/></Cell>
    <Cell><Data ss:Type="Number">92</Data><NamedCell ss:Name="_FilterDatabase"/></Cell>
    <Cell><Data ss:Type="Number">98</Data><NamedCell ss:Name="_FilterDatabase"/></Cell>
    <Cell><Data ss:Type="Boolean">1</Data><NamedCell ss:Name="_FilterDatabase"/></Cell>
   </Row>
   <Row ss:AutoFitHeight="0">
    <Cell ss:StyleID="s62"><Data ss:Type="String">condition15</Data><NamedCell
      ss:Name="_FilterDatabase"/></Cell>
    <Cell><Data ss:Type="Number">92</Data><NamedCell ss:Name="_FilterDatabase"/></Cell>
    <Cell><Data ss:Type="Number">98</Data><NamedCell ss:Name="_FilterDatabase"/></Cell>
    <Cell><Data ss:Type="Boolean">1</Data><NamedCell ss:Name="_FilterDatabase"/></Cell>
   </Row>
   <Row ss:AutoFitHeight="0">
    <Cell ss:StyleID="s62"><Data ss:Type="String">condition16</Data><NamedCell
      ss:Name="_FilterDatabase"/></Cell>
    <Cell><Data ss:Type="Number">92</Data><NamedCell ss:Name="_FilterDatabase"/></Cell>
    <Cell><Data ss:Type="Number">101</Data><NamedCell ss:Name="_FilterDatabase"/></Cell>
    <Cell><Data ss:Type="Boolean">1</Data><NamedCell ss:Name="_FilterDatabase"/></Cell>
   </Row>
   <Row ss:AutoFitHeight="0">
    <Cell ss:StyleID="s62"><Data ss:Type="String">condition17</Data><NamedCell
      ss:Name="_FilterDatabase"/></Cell>
    <Cell><Data ss:Type="Number">92</Data><NamedCell ss:Name="_FilterDatabase"/></Cell>
    <Cell><Data ss:Type="Number">98</Data><NamedCell ss:Name="_FilterDatabase"/></Cell>
    <Cell><Data ss:Type="Boolean">1</Data><NamedCell ss:Name="_FilterDatabase"/></Cell>
   </Row>
   <Row ss:AutoFitHeight="0">
    <Cell ss:StyleID="s62"><Data ss:Type="String">condition18</Data><NamedCell
      ss:Name="_FilterDatabase"/></Cell>
    <Cell><Data ss:Type="Number">92</Data><NamedCell ss:Name="_FilterDatabase"/></Cell>
    <Cell><Data ss:Type="Number">94</Data><NamedCell ss:Name="_FilterDatabase"/></Cell>
    <Cell><Data ss:Type="Boolean">1</Data><NamedCell ss:Name="_FilterDatabase"/></Cell>
   </Row>
   <Row ss:AutoFitHeight="0">
    <Cell ss:StyleID="s62"><Data ss:Type="String">condition19</Data><NamedCell
      ss:Name="_FilterDatabase"/></Cell>
    <Cell><Data ss:Type="Number">92</Data><NamedCell ss:Name="_FilterDatabase"/></Cell>
    <Cell><Data ss:Type="Number">94</Data><NamedCell ss:Name="_FilterDatabase"/></Cell>
    <Cell><Data ss:Type="Boolean">1</Data><NamedCell ss:Name="_FilterDatabase"/></Cell>
   </Row>
   <Row ss:AutoFitHeight="0">
    <Cell ss:StyleID="s62"><Data ss:Type="String">condition20</Data><NamedCell
      ss:Name="_FilterDatabase"/></Cell>
    <Cell><Data ss:Type="Number">92</Data><NamedCell ss:Name="_FilterDatabase"/></Cell>
    <Cell><Data ss:Type="Number">95</Data><NamedCell ss:Name="_FilterDatabase"/></Cell>
    <Cell><Data ss:Type="Boolean">1</Data><NamedCell ss:Name="_FilterDatabase"/></Cell>
   </Row>
   <Row ss:AutoFitHeight="0">
    <Cell ss:StyleID="s62"><Data ss:Type="String">condition21</Data><NamedCell
      ss:Name="_FilterDatabase"/></Cell>
    <Cell><Data ss:Type="Number">7</Data><NamedCell ss:Name="_FilterDatabase"/></Cell>
    <Cell><Data ss:Type="Number">9</Data><NamedCell ss:Name="_FilterDatabase"/></Cell>
    <Cell><Data ss:Type="Boolean">1</Data><NamedCell ss:Name="_FilterDatabase"/></Cell>
   </Row>
   <Row ss:AutoFitHeight="0">
    <Cell ss:StyleID="s62"><Data ss:Type="String">condition22</Data><NamedCell
      ss:Name="_FilterDatabase"/></Cell>
    <Cell><Data ss:Type="Number">26</Data><NamedCell ss:Name="_FilterDatabase"/></Cell>
    <Cell><Data ss:Type="Number">36</Data><NamedCell ss:Name="_FilterDatabase"/></Cell>
    <Cell><Data ss:Type="Boolean">1</Data><NamedCell ss:Name="_FilterDatabase"/></Cell>
   </Row>
   <Row ss:AutoFitHeight="0">
    <Cell ss:StyleID="s62"><Data ss:Type="String">condition23</Data><NamedCell
      ss:Name="_FilterDatabase"/></Cell>
    <Cell><Data ss:Type="Number">92</Data><NamedCell ss:Name="_FilterDatabase"/></Cell>
    <Cell><Data ss:Type="Number">95</Data><NamedCell ss:Name="_FilterDatabase"/></Cell>
    <Cell><Data ss:Type="Boolean">1</Data><NamedCell ss:Name="_FilterDatabase"/></Cell>
   </Row>
   <Row ss:AutoFitHeight="0">
    <Cell ss:StyleID="s62"><Data ss:Type="String">condition24</Data><NamedCell
      ss:Name="_FilterDatabase"/></Cell>
    <Cell><Data ss:Type="Number">92</Data><NamedCell ss:Name="_FilterDatabase"/></Cell>
    <Cell><Data ss:Type="Number">94</Data><NamedCell ss:Name="_FilterDatabase"/></Cell>
    <Cell><Data ss:Type="Boolean">1</Data><NamedCell ss:Name="_FilterDatabase"/></Cell>
   </Row>
   <Row ss:AutoFitHeight="0">
    <Cell ss:StyleID="s62"><Data ss:Type="String">condition25</Data><NamedCell
      ss:Name="_FilterDatabase"/></Cell>
    <Cell><Data ss:Type="Number">93</Data><NamedCell ss:Name="_FilterDatabase"/></Cell>
    <Cell><Data ss:Type="Number">94</Data><NamedCell ss:Name="_FilterDatabase"/></Cell>
    <Cell><Data ss:Type="Boolean">1</Data><NamedCell ss:Name="_FilterDatabase"/></Cell>
   </Row>
   <Row ss:AutoFitHeight="0">
    <Cell ss:StyleID="s62"><Data ss:Type="String">condition26</Data><NamedCell
      ss:Name="_FilterDatabase"/></Cell>
    <Cell><Data ss:Type="Number">93</Data><NamedCell ss:Name="_FilterDatabase"/></Cell>
    <Cell><Data ss:Type="Number">94</Data><NamedCell ss:Name="_FilterDatabase"/></Cell>
    <Cell><Data ss:Type="Boolean">1</Data><NamedCell ss:Name="_FilterDatabase"/></Cell>
   </Row>
   <Row ss:AutoFitHeight="0">
    <Cell ss:StyleID="s62"><Data ss:Type="String">condition27</Data><NamedCell
      ss:Name="_FilterDatabase"/></Cell>
    <Cell><Data ss:Type="Number">93</Data><NamedCell ss:Name="_FilterDatabase"/></Cell>
    <Cell><Data ss:Type="Number">94</Data><NamedCell ss:Name="_FilterDatabase"/></Cell>
    <Cell><Data ss:Type="Boolean">1</Data><NamedCell ss:Name="_FilterDatabase"/></Cell>
   </Row>
   <Row ss:AutoFitHeight="0">
    <Cell ss:StyleID="s62"><Data ss:Type="String">condition28</Data><NamedCell
      ss:Name="_FilterDatabase"/></Cell>
    <Cell><Data ss:Type="Number">93</Data><NamedCell ss:Name="_FilterDatabase"/></Cell>
    <Cell><Data ss:Type="Number">94</Data><NamedCell ss:Name="_FilterDatabase"/></Cell>
    <Cell><Data ss:Type="Boolean">1</Data><NamedCell ss:Name="_FilterDatabase"/></Cell>
   </Row>
   <Row ss:AutoFitHeight="0">
    <Cell ss:StyleID="s62"><Data ss:Type="String">condition29</Data><NamedCell
      ss:Name="_FilterDatabase"/></Cell>
    <Cell><Data ss:Type="Number">98</Data><NamedCell ss:Name="_FilterDatabase"/></Cell>
    <Cell><Data ss:Type="Number">999999</Data><NamedCell ss:Name="_FilterDatabase"/></Cell>
    <Cell><Data ss:Type="Boolean">1</Data><NamedCell ss:Name="_FilterDatabase"/></Cell>
   </Row>
   <Row ss:AutoFitHeight="0">
    <Cell ss:StyleID="s62"><Data ss:Type="String">condition30</Data><NamedCell
      ss:Name="_FilterDatabase"/></Cell>
    <Cell><Data ss:Type="Number">98</Data><NamedCell ss:Name="_FilterDatabase"/></Cell>
    <Cell><Data ss:Type="Number">99</Data><NamedCell ss:Name="_FilterDatabase"/></Cell>
    <Cell><Data ss:Type="Boolean">1</Data><NamedCell ss:Name="_FilterDatabase"/></Cell>
   </Row>
   <Row ss:AutoFitHeight="0">
    <Cell ss:StyleID="s62"><Data ss:Type="String">condition31</Data><NamedCell
      ss:Name="_FilterDatabase"/></Cell>
    <Cell><Data ss:Type="Number">98</Data><NamedCell ss:Name="_FilterDatabase"/></Cell>
    <Cell><Data ss:Type="Number">999999</Data><NamedCell ss:Name="_FilterDatabase"/></Cell>
    <Cell><Data ss:Type="Boolean">1</Data><NamedCell ss:Name="_FilterDatabase"/></Cell>
   </Row>
   <Row ss:AutoFitHeight="0">
    <Cell ss:StyleID="s62"><Data ss:Type="String">condition32</Data><NamedCell
      ss:Name="_FilterDatabase"/></Cell>
    <Cell><Data ss:Type="Number">99</Data><NamedCell ss:Name="_FilterDatabase"/></Cell>
    <Cell><Data ss:Type="Number">100</Data><NamedCell ss:Name="_FilterDatabase"/></Cell>
    <Cell><Data ss:Type="Boolean">1</Data><NamedCell ss:Name="_FilterDatabase"/></Cell>
   </Row>
   <Row ss:AutoFitHeight="0">
    <Cell ss:StyleID="s62"><Data ss:Type="String">condition33</Data><NamedCell
      ss:Name="_FilterDatabase"/></Cell>
    <Cell><Data ss:Type="Number">99</Data><NamedCell ss:Name="_FilterDatabase"/></Cell>
    <Cell><Data ss:Type="Number">104</Data><NamedCell ss:Name="_FilterDatabase"/></Cell>
    <Cell><Data ss:Type="Boolean">1</Data><NamedCell ss:Name="_FilterDatabase"/></Cell>
   </Row>
   <Row ss:AutoFitHeight="0">
    <Cell ss:StyleID="s62"><Data ss:Type="String">condition34</Data><NamedCell
      ss:Name="_FilterDatabase"/></Cell>
    <Cell><Data ss:Type="Number">100</Data><NamedCell ss:Name="_FilterDatabase"/></Cell>
    <Cell><Data ss:Type="Number">109</Data><NamedCell ss:Name="_FilterDatabase"/></Cell>
    <Cell><Data ss:Type="Boolean">1</Data><NamedCell ss:Name="_FilterDatabase"/></Cell>
   </Row>
   <Row ss:AutoFitHeight="0">
    <Cell ss:StyleID="s62"><Data ss:Type="String">condition35</Data><NamedCell
      ss:Name="_FilterDatabase"/></Cell>
    <Cell><Data ss:Type="Number">30</Data><NamedCell ss:Name="_FilterDatabase"/></Cell>
    <Cell><Data ss:Type="Number">999999</Data><NamedCell ss:Name="_FilterDatabase"/></Cell>
    <Cell><Data ss:Type="Boolean">1</Data><NamedCell ss:Name="_FilterDatabase"/></Cell>
   </Row>
   <Row ss:AutoFitHeight="0">
    <Cell ss:StyleID="s62"><Data ss:Type="String">condition36</Data><NamedCell
      ss:Name="_FilterDatabase"/></Cell>
    <Cell><Data ss:Type="Number">91</Data><NamedCell ss:Name="_FilterDatabase"/></Cell>
    <Cell><Data ss:Type="Number">99</Data><NamedCell ss:Name="_FilterDatabase"/></Cell>
    <Cell><Data ss:Type="Boolean">1</Data><NamedCell ss:Name="_FilterDatabase"/></Cell>
   </Row>
   <Row ss:AutoFitHeight="0">
    <Cell ss:StyleID="s62"><Data ss:Type="String">condition37</Data><NamedCell
      ss:Name="_FilterDatabase"/></Cell>
    <Cell><Data ss:Type="Number">98</Data><NamedCell ss:Name="_FilterDatabase"/></Cell>
    <Cell><Data ss:Type="Number">100</Data><NamedCell ss:Name="_FilterDatabase"/></Cell>
    <Cell><Data ss:Type="Boolean">1</Data><NamedCell ss:Name="_FilterDatabase"/></Cell>
   </Row>
   <Row ss:AutoFitHeight="0">
    <Cell ss:StyleID="s62"><Data ss:Type="String">condition38</Data><NamedCell
      ss:Name="_FilterDatabase"/></Cell>
    <Cell><Data ss:Type="Number">99</Data><NamedCell ss:Name="_FilterDatabase"/></Cell>
    <Cell><Data ss:Type="Number">106</Data><NamedCell ss:Name="_FilterDatabase"/></Cell>
    <Cell><Data ss:Type="Boolean">1</Data><NamedCell ss:Name="_FilterDatabase"/></Cell>
   </Row>
   <Row ss:AutoFitHeight="0">
    <Cell ss:StyleID="s62"><Data ss:Type="String">condition39</Data><NamedCell
      ss:Name="_FilterDatabase"/></Cell>
    <Cell><Data ss:Type="Number">18</Data><NamedCell ss:Name="_FilterDatabase"/></Cell>
    <Cell><Data ss:Type="Number">28</Data><NamedCell ss:Name="_FilterDatabase"/></Cell>
    <Cell><Data ss:Type="Boolean">1</Data><NamedCell ss:Name="_FilterDatabase"/></Cell>
   </Row>
   <Row ss:AutoFitHeight="0">
    <Cell ss:StyleID="s62"><Data ss:Type="String">condition40</Data><NamedCell
      ss:Name="_FilterDatabase"/></Cell>
    <Cell><Data ss:Type="Number">103</Data><NamedCell ss:Name="_FilterDatabase"/></Cell>
    <Cell><Data ss:Type="Number">104</Data><NamedCell ss:Name="_FilterDatabase"/></Cell>
    <Cell><Data ss:Type="Boolean">1</Data><NamedCell ss:Name="_FilterDatabase"/></Cell>
   </Row>
   <Row ss:AutoFitHeight="0">
    <Cell ss:StyleID="s62"><Data ss:Type="String">condition41</Data><NamedCell
      ss:Name="_FilterDatabase"/></Cell>
    <Cell><Data ss:Type="Number">98</Data><NamedCell ss:Name="_FilterDatabase"/></Cell>
    <Cell><Data ss:Type="Number">999999</Data><NamedCell ss:Name="_FilterDatabase"/></Cell>
    <Cell><Data ss:Type="Boolean">1</Data><NamedCell ss:Name="_FilterDatabase"/></Cell>
   </Row>
   <Row ss:AutoFitHeight="0">
    <Cell ss:StyleID="s62"><Data ss:Type="String">condition42</Data><NamedCell
      ss:Name="_FilterDatabase"/></Cell>
    <Cell><Data ss:Type="Number">100</Data><NamedCell ss:Name="_FilterDatabase"/></Cell>
    <Cell><Data ss:Type="Number">999999</Data><NamedCell ss:Name="_FilterDatabase"/></Cell>
    <Cell><Data ss:Type="Boolean">1</Data><NamedCell ss:Name="_FilterDatabase"/></Cell>
   </Row>
   <Row ss:AutoFitHeight="0">
    <Cell ss:StyleID="s62"><Data ss:Type="String">condition43</Data><NamedCell
      ss:Name="_FilterDatabase"/></Cell>
    <Cell><Data ss:Type="Number">95</Data><NamedCell ss:Name="_FilterDatabase"/></Cell>
    <Cell><Data ss:Type="Number">97</Data><NamedCell ss:Name="_FilterDatabase"/></Cell>
    <Cell><Data ss:Type="Boolean">1</Data><NamedCell ss:Name="_FilterDatabase"/></Cell>
   </Row>
   <Row ss:AutoFitHeight="0">
    <Cell ss:StyleID="s62"><Data ss:Type="String">condition44</Data><NamedCell
      ss:Name="_FilterDatabase"/></Cell>
    <Cell><Data ss:Type="Number">104</Data><NamedCell ss:Name="_FilterDatabase"/></Cell>
    <Cell><Data ss:Type="Number">110</Data><NamedCell ss:Name="_FilterDatabase"/></Cell>
    <Cell><Data ss:Type="Boolean">1</Data><NamedCell ss:Name="_FilterDatabase"/></Cell>
   </Row>
   <Row ss:AutoFitHeight="0">
    <Cell ss:StyleID="s62"><Data ss:Type="String">condition45</Data><NamedCell
      ss:Name="_FilterDatabase"/></Cell>
    <Cell><Data ss:Type="Number">36</Data><NamedCell ss:Name="_FilterDatabase"/></Cell>
    <Cell><Data ss:Type="Number">39</Data><NamedCell ss:Name="_FilterDatabase"/></Cell>
    <Cell><Data ss:Type="Boolean">1</Data><NamedCell ss:Name="_FilterDatabase"/></Cell>
   </Row>
   <Row ss:AutoFitHeight="0">
    <Cell ss:StyleID="s62"><Data ss:Type="String">condition46</Data><NamedCell
      ss:Name="_FilterDatabase"/></Cell>
    <Cell><Data ss:Type="Number">36</Data><NamedCell ss:Name="_FilterDatabase"/></Cell>
    <Cell><Data ss:Type="Number">999999</Data><NamedCell ss:Name="_FilterDatabase"/></Cell>
    <Cell><Data ss:Type="Boolean">1</Data><NamedCell ss:Name="_FilterDatabase"/></Cell>
   </Row>
   <Row ss:AutoFitHeight="0">
    <Cell ss:StyleID="s62"><Data ss:Type="String">condition47</Data><NamedCell
      ss:Name="_FilterDatabase"/></Cell>
    <Cell><Data ss:Type="Number">99</Data><NamedCell ss:Name="_FilterDatabase"/></Cell>
    <Cell><Data ss:Type="Number">999999</Data><NamedCell ss:Name="_FilterDatabase"/></Cell>
    <Cell><Data ss:Type="Boolean">1</Data><NamedCell ss:Name="_FilterDatabase"/></Cell>
   </Row>
   <Row ss:AutoFitHeight="0">
    <Cell ss:StyleID="s62"><Data ss:Type="String">condition48</Data><NamedCell
      ss:Name="_FilterDatabase"/></Cell>
    <Cell><Data ss:Type="Number">94</Data><NamedCell ss:Name="_FilterDatabase"/></Cell>
    <Cell><Data ss:Type="Number">999999</Data><NamedCell ss:Name="_FilterDatabase"/></Cell>
    <Cell><Data ss:Type="Boolean">1</Data><NamedCell ss:Name="_FilterDatabase"/></Cell>
   </Row>
   <Row ss:AutoFitHeight="0">
    <Cell ss:StyleID="s62"><Data ss:Type="String">condition49</Data><NamedCell
      ss:Name="_FilterDatabase"/></Cell>
    <Cell><Data ss:Type="Number">94</Data><NamedCell ss:Name="_FilterDatabase"/></Cell>
    <Cell><Data ss:Type="Number">95</Data><NamedCell ss:Name="_FilterDatabase"/></Cell>
    <Cell><Data ss:Type="Boolean">1</Data><NamedCell ss:Name="_FilterDatabase"/></Cell>
   </Row>
   <Row ss:AutoFitHeight="0">
    <Cell ss:StyleID="s62"><Data ss:Type="String">condition50</Data><NamedCell
      ss:Name="_FilterDatabase"/></Cell>
    <Cell><Data ss:Type="Number">100</Data><NamedCell ss:Name="_FilterDatabase"/></Cell>
    <Cell><Data ss:Type="Number">101</Data><NamedCell ss:Name="_FilterDatabase"/></Cell>
    <Cell><Data ss:Type="Boolean">1</Data><NamedCell ss:Name="_FilterDatabase"/></Cell>
   </Row>
   <Row ss:AutoFitHeight="0">
    <Cell ss:StyleID="s62"><Data ss:Type="String">condition51</Data><NamedCell
      ss:Name="_FilterDatabase"/></Cell>
    <Cell><Data ss:Type="Number">94</Data><NamedCell ss:Name="_FilterDatabase"/></Cell>
    <Cell><Data ss:Type="Number">95</Data><NamedCell ss:Name="_FilterDatabase"/></Cell>
    <Cell><Data ss:Type="Boolean">1</Data><NamedCell ss:Name="_FilterDatabase"/></Cell>
   </Row>
   <Row ss:AutoFitHeight="0">
    <Cell ss:StyleID="s62"><Data ss:Type="String">condition52</Data><NamedCell
      ss:Name="_FilterDatabase"/></Cell>
    <Cell><Data ss:Type="Number">101</Data><NamedCell ss:Name="_FilterDatabase"/></Cell>
    <Cell><Data ss:Type="Number">999999</Data><NamedCell ss:Name="_FilterDatabase"/></Cell>
    <Cell><Data ss:Type="Boolean">1</Data><NamedCell ss:Name="_FilterDatabase"/></Cell>
   </Row>
   <Row ss:AutoFitHeight="0">
    <Cell ss:StyleID="s62"><Data ss:Type="String">condition53</Data><NamedCell
      ss:Name="_FilterDatabase"/></Cell>
    <Cell><Data ss:Type="Number">104</Data><NamedCell ss:Name="_FilterDatabase"/></Cell>
    <Cell><Data ss:Type="Number">999999</Data><NamedCell ss:Name="_FilterDatabase"/></Cell>
    <Cell><Data ss:Type="Boolean">1</Data><NamedCell ss:Name="_FilterDatabase"/></Cell>
   </Row>
   <Row ss:AutoFitHeight="0">
    <Cell ss:StyleID="s62"><Data ss:Type="String">condition54</Data><NamedCell
      ss:Name="_FilterDatabase"/></Cell>
    <Cell><Data ss:Type="Number">109</Data><NamedCell ss:Name="_FilterDatabase"/></Cell>
    <Cell><Data ss:Type="Number">112</Data><NamedCell ss:Name="_FilterDatabase"/></Cell>
    <Cell><Data ss:Type="Boolean">1</Data><NamedCell ss:Name="_FilterDatabase"/></Cell>
   </Row>
   <Row ss:AutoFitHeight="0">
    <Cell ss:StyleID="s62"><Data ss:Type="String">condition55</Data><NamedCell
      ss:Name="_FilterDatabase"/></Cell>
    <Cell><Data ss:Type="Number">104</Data><NamedCell ss:Name="_FilterDatabase"/></Cell>
    <Cell><Data ss:Type="Number">999999</Data><NamedCell ss:Name="_FilterDatabase"/></Cell>
    <Cell><Data ss:Type="Boolean">1</Data><NamedCell ss:Name="_FilterDatabase"/></Cell>
   </Row>
   <Row ss:AutoFitHeight="0">
    <Cell ss:StyleID="s62"><Data ss:Type="String">condition56</Data><NamedCell
      ss:Name="_FilterDatabase"/></Cell>
    <Cell><Data ss:Type="Number">101</Data><NamedCell ss:Name="_FilterDatabase"/></Cell>
    <Cell><Data ss:Type="Number">999999</Data><NamedCell ss:Name="_FilterDatabase"/></Cell>
    <Cell><Data ss:Type="Boolean">1</Data><NamedCell ss:Name="_FilterDatabase"/></Cell>
   </Row>
   <Row ss:AutoFitHeight="0">
    <Cell ss:StyleID="s62"><Data ss:Type="String">condition57</Data><NamedCell
      ss:Name="_FilterDatabase"/></Cell>
    <Cell><Data ss:Type="Number">100</Data><NamedCell ss:Name="_FilterDatabase"/></Cell>
    <Cell><Data ss:Type="Number">101</Data><NamedCell ss:Name="_FilterDatabase"/></Cell>
    <Cell><Data ss:Type="Boolean">1</Data><NamedCell ss:Name="_FilterDatabase"/></Cell>
   </Row>
   <Row ss:AutoFitHeight="0">
    <Cell ss:StyleID="s62"><Data ss:Type="String">condition58</Data><NamedCell
      ss:Name="_FilterDatabase"/></Cell>
    <Cell><Data ss:Type="Number">98</Data><NamedCell ss:Name="_FilterDatabase"/></Cell>
    <Cell><Data ss:Type="Number">999999</Data><NamedCell ss:Name="_FilterDatabase"/></Cell>
    <Cell><Data ss:Type="Boolean">1</Data><NamedCell ss:Name="_FilterDatabase"/></Cell>
   </Row>
   <Row ss:AutoFitHeight="0">
    <Cell ss:StyleID="s62"><Data ss:Type="String">condition59</Data><NamedCell
      ss:Name="_FilterDatabase"/></Cell>
    <Cell><Data ss:Type="Number">98</Data><NamedCell ss:Name="_FilterDatabase"/></Cell>
    <Cell><Data ss:Type="Number">999999</Data><NamedCell ss:Name="_FilterDatabase"/></Cell>
    <Cell><Data ss:Type="Boolean">1</Data><NamedCell ss:Name="_FilterDatabase"/></Cell>
   </Row>
   <Row ss:AutoFitHeight="0">
    <Cell ss:StyleID="s62"><Data ss:Type="String">condition60</Data><NamedCell
      ss:Name="_FilterDatabase"/></Cell>
    <Cell><Data ss:Type="Number">106</Data><NamedCell ss:Name="_FilterDatabase"/></Cell>
    <Cell><Data ss:Type="Number">999999</Data><NamedCell ss:Name="_FilterDatabase"/></Cell>
    <Cell><Data ss:Type="Boolean">1</Data><NamedCell ss:Name="_FilterDatabase"/></Cell>
   </Row>
   <Row ss:AutoFitHeight="0">
    <Cell ss:StyleID="s62"><Data ss:Type="String">condition61</Data><NamedCell
      ss:Name="_FilterDatabase"/></Cell>
    <Cell><Data ss:Type="Number">106</Data><NamedCell ss:Name="_FilterDatabase"/></Cell>
    <Cell><Data ss:Type="Number">999999</Data><NamedCell ss:Name="_FilterDatabase"/></Cell>
    <Cell><Data ss:Type="Boolean">1</Data><NamedCell ss:Name="_FilterDatabase"/></Cell>
   </Row>
   <Row ss:AutoFitHeight="0">
    <Cell ss:StyleID="s62"><Data ss:Type="String">condition62</Data><NamedCell
      ss:Name="_FilterDatabase"/></Cell>
    <Cell><Data ss:Type="Number">106</Data><NamedCell ss:Name="_FilterDatabase"/></Cell>
    <Cell><Data ss:Type="Number">999999</Data><NamedCell ss:Name="_FilterDatabase"/></Cell>
    <Cell><Data ss:Type="Boolean">1</Data><NamedCell ss:Name="_FilterDatabase"/></Cell>
   </Row>
   <Row ss:AutoFitHeight="0">
    <Cell ss:StyleID="s62"><Data ss:Type="String">condition63</Data><NamedCell
      ss:Name="_FilterDatabase"/></Cell>
    <Cell><Data ss:Type="Number">100</Data><NamedCell ss:Name="_FilterDatabase"/></Cell>
    <Cell><Data ss:Type="Number">999999</Data><NamedCell ss:Name="_FilterDatabase"/></Cell>
    <Cell><Data ss:Type="Boolean">1</Data><NamedCell ss:Name="_FilterDatabase"/></Cell>
   </Row>
   <Row ss:AutoFitHeight="0">
    <Cell ss:StyleID="s62"><Data ss:Type="String">condition64</Data><NamedCell
      ss:Name="_FilterDatabase"/></Cell>
    <Cell><Data ss:Type="Number">98</Data><NamedCell ss:Name="_FilterDatabase"/></Cell>
    <Cell><Data ss:Type="Number">999999</Data><NamedCell ss:Name="_FilterDatabase"/></Cell>
    <Cell><Data ss:Type="Boolean">1</Data><NamedCell ss:Name="_FilterDatabase"/></Cell>
   </Row>
   <Row ss:AutoFitHeight="0">
    <Cell ss:StyleID="s62"><Data ss:Type="String">condition65</Data><NamedCell
      ss:Name="_FilterDatabase"/></Cell>
    <Cell><Data ss:Type="Number">98</Data><NamedCell ss:Name="_FilterDatabase"/></Cell>
    <Cell><Data ss:Type="Number">100</Data><NamedCell ss:Name="_FilterDatabase"/></Cell>
    <Cell><Data ss:Type="Boolean">1</Data><NamedCell ss:Name="_FilterDatabase"/></Cell>
   </Row>
   <Row ss:AutoFitHeight="0">
    <Cell ss:StyleID="s62"><Data ss:Type="String">condition66</Data><NamedCell
      ss:Name="_FilterDatabase"/></Cell>
    <Cell><Data ss:Type="Number">100</Data><NamedCell ss:Name="_FilterDatabase"/></Cell>
    <Cell><Data ss:Type="Number">999999</Data><NamedCell ss:Name="_FilterDatabase"/></Cell>
    <Cell><Data ss:Type="Boolean">1</Data><NamedCell ss:Name="_FilterDatabase"/></Cell>
   </Row>
   <Row ss:AutoFitHeight="0">
    <Cell ss:StyleID="s62"><Data ss:Type="String">condition67</Data><NamedCell
      ss:Name="_FilterDatabase"/></Cell>
    <Cell><Data ss:Type="Number">100</Data><NamedCell ss:Name="_FilterDatabase"/></Cell>
    <Cell><Data ss:Type="Number">999999</Data><NamedCell ss:Name="_FilterDatabase"/></Cell>
    <Cell><Data ss:Type="Boolean">1</Data><NamedCell ss:Name="_FilterDatabase"/></Cell>
   </Row>
   <Row ss:AutoFitHeight="0">
    <Cell ss:StyleID="s62"><Data ss:Type="String">condition68</Data><NamedCell
      ss:Name="_FilterDatabase"/></Cell>
    <Cell><Data ss:Type="Number">95</Data><NamedCell ss:Name="_FilterDatabase"/></Cell>
    <Cell><Data ss:Type="Number">999999</Data><NamedCell ss:Name="_FilterDatabase"/></Cell>
    <Cell><Data ss:Type="Boolean">1</Data><NamedCell ss:Name="_FilterDatabase"/></Cell>
   </Row>
   <Row ss:AutoFitHeight="0">
    <Cell ss:StyleID="s62"><Data ss:Type="String">condition69</Data><NamedCell
      ss:Name="_FilterDatabase"/></Cell>
    <Cell><Data ss:Type="Number">94</Data><NamedCell ss:Name="_FilterDatabase"/></Cell>
    <Cell><Data ss:Type="Number">999999</Data><NamedCell ss:Name="_FilterDatabase"/></Cell>
    <Cell><Data ss:Type="Boolean">1</Data><NamedCell ss:Name="_FilterDatabase"/></Cell>
   </Row>
   <Row ss:AutoFitHeight="0">
    <Cell ss:StyleID="s62"><Data ss:Type="String">condition70</Data><NamedCell
      ss:Name="_FilterDatabase"/></Cell>
    <Cell><Data ss:Type="Number">39</Data><NamedCell ss:Name="_FilterDatabase"/></Cell>
    <Cell><Data ss:Type="Number">999999</Data><NamedCell ss:Name="_FilterDatabase"/></Cell>
    <Cell><Data ss:Type="Boolean">1</Data><NamedCell ss:Name="_FilterDatabase"/></Cell>
   </Row>
   <Row ss:AutoFitHeight="0">
    <Cell ss:StyleID="s62"><Data ss:Type="String">condition71</Data><NamedCell
      ss:Name="_FilterDatabase"/></Cell>
    <Cell><Data ss:Type="Number">24</Data><NamedCell ss:Name="_FilterDatabase"/></Cell>
    <Cell><Data ss:Type="Number">999999</Data><NamedCell ss:Name="_FilterDatabase"/></Cell>
    <Cell><Data ss:Type="Boolean">1</Data><NamedCell ss:Name="_FilterDatabase"/></Cell>
   </Row>
   <Row ss:AutoFitHeight="0">
    <Cell ss:StyleID="s62"><Data ss:Type="String">condition72</Data><NamedCell
      ss:Name="_FilterDatabase"/></Cell>
    <Cell><Data ss:Type="Number">28</Data><NamedCell ss:Name="_FilterDatabase"/></Cell>
    <Cell><Data ss:Type="Number">999999</Data><NamedCell ss:Name="_FilterDatabase"/></Cell>
    <Cell><Data ss:Type="Boolean">1</Data><NamedCell ss:Name="_FilterDatabase"/></Cell>
   </Row>
   <Row ss:AutoFitHeight="0">
    <Cell ss:StyleID="s62"><Data ss:Type="String">condition73</Data><NamedCell
      ss:Name="_FilterDatabase"/></Cell>
    <Cell><Data ss:Type="Number">24</Data><NamedCell ss:Name="_FilterDatabase"/></Cell>
    <Cell><Data ss:Type="Number">999999</Data><NamedCell ss:Name="_FilterDatabase"/></Cell>
    <Cell><Data ss:Type="Boolean">1</Data><NamedCell ss:Name="_FilterDatabase"/></Cell>
   </Row>
   <Row ss:AutoFitHeight="0">
    <Cell ss:StyleID="s62"><Data ss:Type="String">condition74</Data><NamedCell
      ss:Name="_FilterDatabase"/></Cell>
    <Cell><Data ss:Type="Number">94</Data><NamedCell ss:Name="_FilterDatabase"/></Cell>
    <Cell><Data ss:Type="Number">999999</Data><NamedCell ss:Name="_FilterDatabase"/></Cell>
    <Cell><Data ss:Type="Boolean">1</Data><NamedCell ss:Name="_FilterDatabase"/></Cell>
   </Row>
   <Row ss:AutoFitHeight="0">
    <Cell ss:StyleID="s62"><Data ss:Type="String">condition75</Data><NamedCell
      ss:Name="_FilterDatabase"/></Cell>
    <Cell><Data ss:Type="Number">97</Data><NamedCell ss:Name="_FilterDatabase"/></Cell>
    <Cell><Data ss:Type="Number">999999</Data><NamedCell ss:Name="_FilterDatabase"/></Cell>
    <Cell><Data ss:Type="Boolean">1</Data><NamedCell ss:Name="_FilterDatabase"/></Cell>
   </Row>
   <Row ss:AutoFitHeight="0">
    <Cell ss:StyleID="s62"><Data ss:Type="String">condition76</Data><NamedCell
      ss:Name="_FilterDatabase"/></Cell>
    <Cell><Data ss:Type="Number">94</Data><NamedCell ss:Name="_FilterDatabase"/></Cell>
    <Cell><Data ss:Type="Number">999999</Data><NamedCell ss:Name="_FilterDatabase"/></Cell>
    <Cell><Data ss:Type="Boolean">1</Data><NamedCell ss:Name="_FilterDatabase"/></Cell>
   </Row>
   <Row ss:AutoFitHeight="0">
    <Cell ss:StyleID="s62"><Data ss:Type="String">condition77</Data><NamedCell
      ss:Name="_FilterDatabase"/></Cell>
    <Cell><Data ss:Type="Number">94</Data><NamedCell ss:Name="_FilterDatabase"/></Cell>
    <Cell><Data ss:Type="Number">999999</Data><NamedCell ss:Name="_FilterDatabase"/></Cell>
    <Cell><Data ss:Type="Boolean">1</Data><NamedCell ss:Name="_FilterDatabase"/></Cell>
   </Row>
   <Row ss:AutoFitHeight="0">
    <Cell ss:StyleID="s62"><Data ss:Type="String">condition78</Data><NamedCell
      ss:Name="_FilterDatabase"/></Cell>
    <Cell><Data ss:Type="Number">94</Data><NamedCell ss:Name="_FilterDatabase"/></Cell>
    <Cell><Data ss:Type="Number">97</Data><NamedCell ss:Name="_FilterDatabase"/></Cell>
    <Cell><Data ss:Type="Boolean">1</Data><NamedCell ss:Name="_FilterDatabase"/></Cell>
   </Row>
   <Row ss:AutoFitHeight="0">
    <Cell ss:StyleID="s62"><Data ss:Type="String">condition79</Data><NamedCell
      ss:Name="_FilterDatabase"/></Cell>
    <Cell><Data ss:Type="Number">94</Data><NamedCell ss:Name="_FilterDatabase"/></Cell>
    <Cell><Data ss:Type="Number">999999</Data><NamedCell ss:Name="_FilterDatabase"/></Cell>
    <Cell><Data ss:Type="Boolean">1</Data><NamedCell ss:Name="_FilterDatabase"/></Cell>
   </Row>
   <Row ss:AutoFitHeight="0">
    <Cell ss:StyleID="s62"><Data ss:Type="String">condition80</Data><NamedCell
      ss:Name="_FilterDatabase"/></Cell>
    <Cell><Data ss:Type="Number">94</Data><NamedCell ss:Name="_FilterDatabase"/></Cell>
    <Cell><Data ss:Type="Number">999999</Data><NamedCell ss:Name="_FilterDatabase"/></Cell>
    <Cell><Data ss:Type="Boolean">1</Data><NamedCell ss:Name="_FilterDatabase"/></Cell>
   </Row>
   <Row ss:AutoFitHeight="0">
    <Cell ss:StyleID="s62"><Data ss:Type="String">condition81</Data><NamedCell
      ss:Name="_FilterDatabase"/></Cell>
    <Cell><Data ss:Type="Number">95</Data><NamedCell ss:Name="_FilterDatabase"/></Cell>
    <Cell><Data ss:Type="Number">999999</Data><NamedCell ss:Name="_FilterDatabase"/></Cell>
    <Cell><Data ss:Type="Boolean">1</Data><NamedCell ss:Name="_FilterDatabase"/></Cell>
   </Row>
   <Row ss:AutoFitHeight="0">
    <Cell ss:StyleID="s62"><Data ss:Type="String">condition82</Data><NamedCell
      ss:Name="_FilterDatabase"/></Cell>
    <Cell><Data ss:Type="Number">95</Data><NamedCell ss:Name="_FilterDatabase"/></Cell>
    <Cell><Data ss:Type="Number">999999</Data><NamedCell ss:Name="_FilterDatabase"/></Cell>
    <Cell><Data ss:Type="Boolean">1</Data><NamedCell ss:Name="_FilterDatabase"/></Cell>
   </Row>
   <Row ss:AutoFitHeight="0">
    <Cell ss:StyleID="s62"><Data ss:Type="String">condition83</Data><NamedCell
      ss:Name="_FilterDatabase"/></Cell>
    <Cell><Data ss:Type="Number">9</Data><NamedCell ss:Name="_FilterDatabase"/></Cell>
    <Cell><Data ss:Type="Number">12</Data><NamedCell ss:Name="_FilterDatabase"/></Cell>
    <Cell><Data ss:Type="Boolean">1</Data><NamedCell ss:Name="_FilterDatabase"/></Cell>
   </Row>
   <Row ss:AutoFitHeight="0">
    <Cell ss:StyleID="s62"><Data ss:Type="String">condition84</Data><NamedCell
      ss:Name="_FilterDatabase"/></Cell>
    <Cell><Data ss:Type="Number">94</Data><NamedCell ss:Name="_FilterDatabase"/></Cell>
    <Cell><Data ss:Type="Number">999999</Data><NamedCell ss:Name="_FilterDatabase"/></Cell>
    <Cell><Data ss:Type="Boolean">1</Data><NamedCell ss:Name="_FilterDatabase"/></Cell>
   </Row>
   <Row ss:AutoFitHeight="0">
    <Cell ss:StyleID="s62"><Data ss:Type="String">condition85</Data><NamedCell
      ss:Name="_FilterDatabase"/></Cell>
    <Cell><Data ss:Type="Number">94</Data><NamedCell ss:Name="_FilterDatabase"/></Cell>
    <Cell><Data ss:Type="Number">999999</Data><NamedCell ss:Name="_FilterDatabase"/></Cell>
    <Cell><Data ss:Type="Boolean">1</Data><NamedCell ss:Name="_FilterDatabase"/></Cell>
   </Row>
   <Row ss:AutoFitHeight="0">
    <Cell ss:StyleID="s62"><Data ss:Type="String">condition86</Data><NamedCell
      ss:Name="_FilterDatabase"/></Cell>
    <Cell><Data ss:Type="Number">94</Data><NamedCell ss:Name="_FilterDatabase"/></Cell>
    <Cell><Data ss:Type="Number">999999</Data><NamedCell ss:Name="_FilterDatabase"/></Cell>
    <Cell><Data ss:Type="Boolean">1</Data><NamedCell ss:Name="_FilterDatabase"/></Cell>
   </Row>
   <Row ss:AutoFitHeight="0">
    <Cell ss:StyleID="s62"><Data ss:Type="String">condition87</Data><NamedCell
      ss:Name="_FilterDatabase"/></Cell>
    <Cell><Data ss:Type="Number">94</Data><NamedCell ss:Name="_FilterDatabase"/></Cell>
    <Cell><Data ss:Type="Number">999999</Data><NamedCell ss:Name="_FilterDatabase"/></Cell>
    <Cell><Data ss:Type="Boolean">1</Data><NamedCell ss:Name="_FilterDatabase"/></Cell>
   </Row>
   <Row ss:AutoFitHeight="0">
    <Cell ss:StyleID="s62"><Data ss:Type="String">condition88</Data><NamedCell
      ss:Name="_FilterDatabase"/></Cell>
    <Cell><Data ss:Type="Number">94</Data><NamedCell ss:Name="_FilterDatabase"/></Cell>
    <Cell><Data ss:Type="Number">999999</Data><NamedCell ss:Name="_FilterDatabase"/></Cell>
    <Cell><Data ss:Type="Boolean">1</Data><NamedCell ss:Name="_FilterDatabase"/></Cell>
   </Row>
   <Row ss:AutoFitHeight="0">
    <Cell ss:StyleID="s62"><Data ss:Type="String">condition89</Data><NamedCell
      ss:Name="_FilterDatabase"/></Cell>
    <Cell><Data ss:Type="Number">94</Data><NamedCell ss:Name="_FilterDatabase"/></Cell>
    <Cell><Data ss:Type="Number">999999</Data><NamedCell ss:Name="_FilterDatabase"/></Cell>
    <Cell><Data ss:Type="Boolean">1</Data><NamedCell ss:Name="_FilterDatabase"/></Cell>
   </Row>
   <Row ss:AutoFitHeight="0">
    <Cell ss:StyleID="s62"><Data ss:Type="String">condition90</Data><NamedCell
      ss:Name="_FilterDatabase"/></Cell>
    <Cell><Data ss:Type="Number">101</Data><NamedCell ss:Name="_FilterDatabase"/></Cell>
    <Cell><Data ss:Type="Number">999999</Data><NamedCell ss:Name="_FilterDatabase"/></Cell>
    <Cell><Data ss:Type="Boolean">1</Data><NamedCell ss:Name="_FilterDatabase"/></Cell>
   </Row>
   <Row ss:AutoFitHeight="0">
    <Cell ss:StyleID="s62"><Data ss:Type="String">condition91</Data><NamedCell
      ss:Name="_FilterDatabase"/></Cell>
    <Cell><Data ss:Type="Number">110</Data><NamedCell ss:Name="_FilterDatabase"/></Cell>
    <Cell><Data ss:Type="Number">113</Data><NamedCell ss:Name="_FilterDatabase"/></Cell>
    <Cell><Data ss:Type="Boolean">1</Data><NamedCell ss:Name="_FilterDatabase"/></Cell>
   </Row>
   <Row ss:AutoFitHeight="0">
    <Cell ss:StyleID="s62"><Data ss:Type="String">condition92</Data><NamedCell
      ss:Name="_FilterDatabase"/></Cell>
    <Cell><Data ss:Type="Number">112</Data><NamedCell ss:Name="_FilterDatabase"/></Cell>
    <Cell><Data ss:Type="Number">113</Data><NamedCell ss:Name="_FilterDatabase"/></Cell>
    <Cell><Data ss:Type="Boolean">1</Data><NamedCell ss:Name="_FilterDatabase"/></Cell>
   </Row>
   <Row ss:AutoFitHeight="0">
    <Cell ss:StyleID="s62"><Data ss:Type="String">condition93</Data><NamedCell
      ss:Name="_FilterDatabase"/></Cell>
    <Cell><Data ss:Type="Number">113</Data><NamedCell ss:Name="_FilterDatabase"/></Cell>
    <Cell><Data ss:Type="Number">999999</Data><NamedCell ss:Name="_FilterDatabase"/></Cell>
    <Cell><Data ss:Type="Boolean">1</Data><NamedCell ss:Name="_FilterDatabase"/></Cell>
   </Row>
   <Row ss:AutoFitHeight="0">
    <Cell ss:StyleID="s62"><Data ss:Type="String">condition94</Data></Cell>
    <Cell><Data ss:Type="Number">93</Data></Cell>
    <Cell><Data ss:Type="Number">999999</Data></Cell>
    <Cell><Data ss:Type="Boolean">1</Data></Cell>
   </Row>
   <Row ss:AutoFitHeight="0">
    <Cell ss:StyleID="s62"><Data ss:Type="String">condition95</Data></Cell>
    <Cell><Data ss:Type="Number">113</Data></Cell>
    <Cell><Data ss:Type="Number">999999</Data></Cell>
    <Cell><Data ss:Type="Boolean">1</Data></Cell>
   </Row>
   <Row ss:AutoFitHeight="0">
    <Cell ss:StyleID="s62"><Data ss:Type="String">condition96</Data></Cell>
    <Cell><Data ss:Type="Number">107</Data></Cell>
    <Cell><Data ss:Type="Number">999999</Data></Cell>
    <Cell><Data ss:Type="Boolean">1</Data></Cell>
   </Row>
   <Row ss:AutoFitHeight="0">
    <Cell ss:StyleID="s62"><Data ss:Type="String">condition97</Data></Cell>
    <Cell><Data ss:Type="Number">106</Data></Cell>
    <Cell><Data ss:Type="Number">999999</Data></Cell>
    <Cell><Data ss:Type="Boolean">1</Data></Cell>
   </Row>
   <Row ss:AutoFitHeight="0">
    <Cell ss:StyleID="s62"><Data ss:Type="String">condition98</Data></Cell>
    <Cell><Data ss:Type="Number">97</Data></Cell>
    <Cell><Data ss:Type="Number">999999</Data></Cell>
    <Cell><Data ss:Type="Boolean">1</Data></Cell>
   </Row>
   <Row ss:AutoFitHeight="0">
    <Cell ss:StyleID="s62"><Data ss:Type="String">condition99</Data></Cell>
    <Cell><Data ss:Type="Number">12</Data></Cell>
    <Cell><Data ss:Type="Number">999999</Data></Cell>
    <Cell><Data ss:Type="Boolean">1</Data></Cell>
   </Row>
   <Row ss:AutoFitHeight="0">
    <Cell ss:StyleID="s62"><Data ss:Type="String">condition100</Data></Cell>
    <Cell><Data ss:Type="Number">100</Data></Cell>
    <Cell><Data ss:Type="Number">999999</Data></Cell>
    <Cell><Data ss:Type="Boolean">1</Data></Cell>
   </Row>
   <Row ss:AutoFitHeight="0">
    <Cell ss:StyleID="s62"><Data ss:Type="String">condition101</Data></Cell>
    <Cell><Data ss:Type="Number">97</Data></Cell>
    <Cell><Data ss:Type="Number">999999</Data></Cell>
    <Cell><Data ss:Type="Boolean">1</Data></Cell>
   </Row>
   <Row ss:AutoFitHeight="0">
    <Cell ss:StyleID="s62"><Data ss:Type="String">condition102</Data></Cell>
    <Cell><Data ss:Type="Number">97</Data></Cell>
    <Cell><Data ss:Type="Number">999999</Data></Cell>
    <Cell><Data ss:Type="Boolean">1</Data></Cell>
   </Row>
   <Row ss:AutoFitHeight="0">
    <Cell ss:StyleID="s62"><Data ss:Type="String">condition103</Data></Cell>
    <Cell><Data ss:Type="Number">108</Data></Cell>
    <Cell><Data ss:Type="Number">999999</Data></Cell>
    <Cell><Data ss:Type="Boolean">1</Data></Cell>
   </Row>
   <Row ss:AutoFitHeight="0">
    <Cell ss:StyleID="s62"><Data ss:Type="String">condition104</Data></Cell>
    <Cell><Data ss:Type="Number">104</Data></Cell>
    <Cell><Data ss:Type="Number">999999</Data></Cell>
    <Cell><Data ss:Type="Boolean">1</Data></Cell>
   </Row>
  </Table>
  <WorksheetOptions xmlns="urn:schemas-microsoft-com:office:excel">
   <PageSetup>
    <Header x:Margin="0.3"/>
    <Footer x:Margin="0.3"/>
    <PageMargins x:Bottom="0.75" x:Left="0.7" x:Right="0.7" x:Top="0.75"/>
   </PageSetup>
   <Unsynced/>
   <Print>
    <ValidPrinterInfo/>
    <PaperSizeIndex>9</PaperSizeIndex>
    <HorizontalResolution>600</HorizontalResolution>
    <VerticalResolution>600</VerticalResolution>
   </Print>
   <Selected/>
   <TopRowVisible>86</TopRowVisible>
   <Panes>
    <Pane>
     <Number>3</Number>
     <ActiveRow>107</ActiveRow>
     <ActiveCol>1</ActiveCol>
    </Pane>
   </Panes>
   <ProtectObjects>False</ProtectObjects>
   <ProtectScenarios>False</ProtectScenarios>
  </WorksheetOptions>
  <AutoFilter x:Range="R1C1:R95C4"
   xmlns="urn:schemas-microsoft-com:office:excel">
  </AutoFilter>
 </Worksheet>
</Workbook>
